{
  "success": 1,
  "pager": {
    "page": 1,
    "per_page": 1000,
    "total": 5
  },
  "results": [
    {
      "id": "181155766",
      "sport_id": "18",
      "time": "1757603948",
      "time_status": "1",
      "league": {
        "id": "10086558",
        "name": "Testing Hoops"
      },
      "home": {
        "id": "10476996",
        "name": "China Test"
      },
      "away": {
        "id": "10476997",
        "name": "England Test"
      },
      "ss": "36-39",
      "our_event_id": "10649332",
      "r_id": "181155766C18A",
      "ev_id": "151811559225C18",
      "updated_at": "1757653986"
    },
    {
      "id": "181096267",
      "sport_id": "18",
      "time": "1757644200",
      "time_status": "1",
      "league": {
        "id": "10072595",
        "name": "Mexico LBP"
      },
      "home": {
        "id": "11194198",
        "name": "Fohr"
      },
      "away": {
        "id": "11220726",
        "name": "Iguanas"
      },
      "ss": "47-53",
      "our_event_id": "10647994",
      "r_id": "181096267C18A",
      "ev_id": "151811001885C18",
      "updated_at": "1757653985"
    },
    {
      "id": "181162813",
      "sport_id": "18",
      "time": "1757653200",
      "time_status": "1",
      "league": {
        "id": "10085324",
        "name": "Korea University League Women"
      },
      "home": {
        "id": "11326866",
        "name": "Suwon University (W)"
      },
      "away": {
        "id": "11331004",
        "name": "Ulsan University (W)"
      },
      "ss": "21-5",
      "our_event_id": "10650843",
      "r_id": "181162813C18A",
      "ev_id": "151811639375C18",
      "updated_at": "1757653985"
    },
    {
      "id": "181160727",
      "sport_id": "18",
      "time": "1757653531",
      "time_status": "1",
      "league": {
        "id": "10068518",
        "name": "Ebasketball H2H GG League - 4x5mins"
      },
      "home": {
        "id": "11283224",
        "name": "CLE Cavaliers (OCEAN)"
      },
      "away": {
        "id": "11233245",
        "name": "PHX Suns (OREZ)"
      },
      "ss": "2-7",
      "our_event_id": "10652257",
      "r_id": "181160727C18A",
      "ev_id": "151811608465C18",
      "updated_at": "1757653986"
    },
    {
      "id": "181132336",
      "sport_id": "18",
      "time": "1757653620",
      "time_status": "1",
      "league": {
        "id": "10068518",
        "name": "Ebasketball H2H GG League - 4x5mins"
      },
      "home": {
        "id": "11277122",
        "name": "CHA Hornets (TAAPZ)"
      },
      "away": {
        "id": "11282422",
        "name": "ORL Magic (CURSE)"
      },
      "ss": "9-7",
      "our_event_id": "10652220",
      "r_id": "181132336C18A",
      "ev_id": "151811337515C18",
      "updated_at": "1757653986"
    }
  ]
}